report_template/BeautifulReport.py
report_template/__init__.py
report_template/template/template.html
report_template/template/theme.json
report_template/template/theme_candy.json
report_template/template/theme_cyan.json
report_template/template/theme_default.json
report_template/template/theme_memories.json
report_platform-0.0.6.dist-info/LICENSE.txt
report_platform-0.0.6.dist-info/METADATA
report_platform-0.0.6.dist-info/WHEEL
report_platform-0.0.6.dist-info/top_level.txt
report_platform-0.0.6.dist-info/RECORD
