Metadata-Version: 2.1
Name: report-platform
Version: 0.0.6
Summary: report
Home-page: https://gitee.com/code-smarting/report-platform.git
Author: Freeman
Author-email: 1625077590@qq.com
License: UNKNOWN
Platform: UNKNOWN
Classifier: Programming Language :: Python :: 3
Classifier: License :: OSI Approved :: MIT License
Classifier: Operating System :: OS Independent
Requires-Python: >=3.7
License-File: LICENSE.txt
